[
  {
    "subject_code": "UC0038",
    "course_department": "GIST College (Common)",
    "course_code": "UC0038-01",
    "course_title": "Next-generation energy technologies for achieving carbon neutrality and RE100",
    "course_type": "E",
    "instructor": "",
    "course_credit": "1",
    "course_time": "TUE 10:30~12:00",
    "class_size": "30",
    "grading": "S/U"
  },
  {
    "subject_code": "UC0039",
    "course_department": "GIST College (Common)",
    "course_code": "UC0039-01",
    "course_title": "Entrepreneurial Leadership and Corporate Culture",
    "course_type": "E",
    "instructor": "",
    "course_credit": "3",
    "course_time": "WED 14:00~17:00",
    "class_size": "22",
    "grading": "Letter"
  },
  {
    "subject_code": "UC0201",
    "course_department": "GIST College (Common)",
    "course_code": "UC0201-01",
    "course_title": "Volunteer Social Service",
    "course_type": "E",
    "instructor": "Kim, Jae Gwan",
    "course_credit": "1",
    "course_time": "FRI 10:30~12:00",
    "class_size": "0",
    "grading": "S/U"
  },
  {
    "subject_code": "UC0613",
    "course_department": "GIST College (Common)",
    "course_code": "UC0613-01",
    "course_title": "",
    "course_type": "E",
    "instructor": "Kangmo Choi",
    "course_credit": "3",
    "course_time": "FRI 15:00~18:00",
    "class_size": "22",
    "grading": "Letter"
  },
  {
    "subject_code": "UC0623",
    "course_department": "GIST College (Common)",
    "course_code": "UC0623-01",
    "course_title": "",
    "course_type": "E",
    "instructor": "",
    "course_credit": "3",
    "course_time": "TUE 13:00~16:00",
    "class_size": "22",
    "grading": "Letter"
  },
  {
    "subject_code": "UC0624",
    "course_department": "GIST College (Common)",
    "course_code": "UC0624-01",
    "course_title": "",
    "course_type": "E",
    "instructor": "",
    "course_credit": "3",
    "course_time": "TUE 09:00~12:00",
    "class_size": "22",
    "grading": "Letter"
  },
  {
    "subject_code": "UC0901",
    "course_department": "GIST College (Common)",
    "course_code": "UC0901-01",
    "course_title": "Science, Technology and Economy",
    "course_type": "E",
    "instructor": "Hwang In Seong",
    "course_credit": "1",
    "course_time": "TUE 16:00~17:30",
    "class_size": "270",
    "grading": "S/U"
  },
  {
    "subject_code": "UC9331",
    "course_department": "GIST College (Common)",
    "course_code": "UC9331-01",
    "course_title": "GIST College Colloquium",
    "course_type": "R",
    "instructor": "Hwang, Eui Seok",
    "course_credit": "0",
    "course_time": "THU 16:00~17:30",
    "class_size": "200",
    "grading": "S/U"
  }
]